meterelf/__init__.py
meterelf/__main__.py
meterelf/_api.py
meterelf/_calibration.py
meterelf/_colors.py
meterelf/_debug.py
meterelf/_dial_data.py
meterelf/_image.py
meterelf/_main.py
meterelf/_params.py
meterelf/_reading.py
meterelf/_template_matching.py
meterelf/_types.py
meterelf/_utils.py
waterwatch/__init__.py
waterwatch/__main__.py
meterelf-0.1.0.dist-info/LICENSE
meterelf-0.1.0.dist-info/METADATA
meterelf-0.1.0.dist-info/WHEEL
meterelf-0.1.0.dist-info/entry_points.txt
meterelf-0.1.0.dist-info/top_level.txt
meterelf-0.1.0.dist-info/RECORD
